minebase/__init__.py
minebase/py.typed
minebase/data/.git
minebase/data/README.md
minebase/data/.github/FUNDING.yml
minebase/data/.github/ISSUE_TEMPLATE/blank_issue.md
minebase/data/.github/ISSUE_TEMPLATE/new_version.md
minebase/data/.github/helper-bot/index.js
minebase/data/.github/workflows/bedrock-ci.yml
minebase/data/.github/workflows/build-gh-pages.yml
minebase/data/.github/workflows/ci.yml
minebase/data/.github/workflows/commands.yml
minebase/data/.github/workflows/tag.yml
minebase/data/.github/workflows/update-helper.yml
minebase/data/data/dataPaths.json
minebase/data/data/bedrock/0.14/blocks.json
minebase/data/data/bedrock/0.14/items.json
minebase/data/data/bedrock/0.14/protocol.json
minebase/data/data/bedrock/0.14/version.json
minebase/data/data/bedrock/0.15/blocks.json
minebase/data/data/bedrock/0.15/items.json
minebase/data/data/bedrock/0.15/protocol.json
minebase/data/data/bedrock/0.15/version.json
minebase/data/data/bedrock/1.0/blocks.json
minebase/data/data/bedrock/1.0/items.json
minebase/data/data/bedrock/1.0/version.json
minebase/data/data/bedrock/1.16.201/attributes.json
minebase/data/data/bedrock/1.16.201/enchantments.json
minebase/data/data/bedrock/1.16.201/language.json
minebase/data/data/bedrock/1.16.201/proto.yml
minebase/data/data/bedrock/1.16.201/protocol.json
minebase/data/data/bedrock/1.16.201/steve.json
minebase/data/data/bedrock/1.16.201/types.yml
minebase/data/data/bedrock/1.16.201/version.json
minebase/data/data/bedrock/1.16.201/windows.json
minebase/data/data/bedrock/1.16.210/language.json
minebase/data/data/bedrock/1.16.210/proto.yml
minebase/data/data/bedrock/1.16.210/protocol.json
minebase/data/data/bedrock/1.16.210/types.yml
minebase/data/data/bedrock/1.16.210/version.json
minebase/data/data/bedrock/1.16.220/blockStates.json
minebase/data/data/bedrock/1.16.220/blocks.json
minebase/data/data/bedrock/1.16.220/language.json
minebase/data/data/bedrock/1.16.220/proto.yml
minebase/data/data/bedrock/1.16.220/protocol.json
minebase-0.3.0.dist-info/METADATA
minebase-0.3.0.dist-info/WHEEL
minebase-0.3.0.dist-info/licenses/LICENSE.txt
minebase-0.3.0.dist-info/RECORD
