Metadata-Version: 2.4
Name: minebase
Version: 0.3.0
Summary: Library providing an interface to minecraft-data
Project-URL: Source code, https://github.com/py-mine/minebase
Author-email: ItsDrike <itsdrike@protonmail.com>
Maintainer-email: ItsDrike <itsdrike@protonmail.com>
License-Expression: LGPL-3.0-or-later
License-File: LICENSE.txt
Keywords: data,minecraft
Classifier: Development Status :: 2 - Pre-Alpha
Classifier: Intended Audience :: Developers
Classifier: License :: OSI Approved :: GNU Lesser General Public License v3 or later (LGPLv3+)
Classifier: Natural Language :: English
Classifier: Operating System :: OS Independent
Classifier: Programming Language :: Python
Classifier: Programming Language :: Python :: 3
Classifier: Programming Language :: Python :: 3.9
Classifier: Programming Language :: Python :: 3.10
Classifier: Programming Language :: Python :: 3.11
Classifier: Programming Language :: Python :: 3.12
Classifier: Programming Language :: Python :: 3.13
Classifier: Topic :: Games/Entertainment
Classifier: Topic :: Software Development :: Libraries
Classifier: Topic :: Software Development :: Libraries :: Python Modules
Classifier: Typing :: Typed
Requires-Python: >=3.9
